README.md
setup.py
vortex/__init__.py
vortex/main.py
vortex.egg-info/PKG-INFO
vortex.egg-info/SOURCES.txt
vortex.egg-info/dependency_links.txt
vortex.egg-info/top_level.txt