Metadata-Version: 2.1
Name: vortex
Version: 0.1.3
Summary: A Python API to predict the quality of an hackathon idea using machine learning.
Home-page: https://pypi.org/project/vortex/
Author: Mat Kallada
Author-email: matkallada@gmail.com
License: UNKNOWN
Keywords: machine learning,naive bayes,example
Platform: UNKNOWN
